sigil/__init__.py
sigil-0.1.dist-info/METADATA
sigil-0.1.dist-info/WHEEL
sigil-0.1.dist-info/top_level.txt
sigil-0.1.dist-info/RECORD
